django_model_path_converter-0.1.0.dist-info/METADATA
django_model_path_converter-0.1.0.dist-info/RECORD
django_model_path_converter-0.1.0.dist-info/WHEEL
django_model_path_converter-0.1.0.dist-info/top_level.txt
model_path_converter/__init__.py
