Metadata-Version: 2.1
Name: django-model-path-converter
Version: 0.1.0
Summary: The Django Model Path Converter package dynamically creates custom path converters for you models.
Home-page: https://github.com/dhepper/django-model-path-converter
Author: Daniel Hepper
Author-email: daniel@consideratecode.com
License: MIT license
Keywords: django-model-path-converter
Platform: UNKNOWN
Classifier: Development Status :: 2 - Pre-Alpha
Classifier: Intended Audience :: Developers
Classifier: License :: OSI Approved :: MIT License
Classifier: Natural Language :: English
Classifier: Programming Language :: Python :: 3
Classifier: Programming Language :: Python :: 3 :: Only
Classifier: Programming Language :: Python :: 3.4
Classifier: Programming Language :: Python :: 3.5
Classifier: Programming Language :: Python :: 3.6
Classifier: Framework :: Django
Requires-Dist: django (>=2)
